examples/__init__.py
examples/apollo_engine_reporting_example.py
examples/example.py
graphene_tornado/__init__.py
graphene_tornado/extension_stack.py
graphene_tornado/graphql_extension.py
graphene_tornado/render_graphiql.py
graphene_tornado/request_context.py
graphene_tornado/schema.py
graphene_tornado/tornado_graphql_handler.py
graphene_tornado/apollo_tooling/__init__.py
graphene_tornado/apollo_tooling/operation_id.py
graphene_tornado/apollo_tooling/query_hash.py
graphene_tornado/apollo_tooling/seperate_operations.py
graphene_tornado/apollo_tooling/transforms.py
graphene_tornado/apollo_tooling/tests/__init__.py
graphene_tornado/apollo_tooling/tests/test_operation_id.py
graphene_tornado/apollo_tooling/tests/test_transforms.py
graphene_tornado/ext/__init__.py
graphene_tornado/ext/extension_helpers.py
graphene_tornado/ext/apollo_engine_reporting/__init__.py
graphene_tornado/ext/apollo_engine_reporting/engine_agent.py
graphene_tornado/ext/apollo_engine_reporting/engine_extension.py
graphene_tornado/ext/apollo_engine_reporting/reports_pb2.py
graphene_tornado/ext/apollo_engine_reporting/schema_utils.py
graphene_tornado/ext/apollo_engine_reporting/tests/__init__.py
graphene_tornado/ext/apollo_engine_reporting/tests/schema.py
graphene_tornado/ext/apollo_engine_reporting/tests/test_engine_agent.py
graphene_tornado/ext/apollo_engine_reporting/tests/test_engine_agent_integration.py
graphene_tornado/ext/apollo_engine_reporting/tests/test_engine_extension.py
graphene_tornado/ext/opencensus/__init__.py
graphene_tornado/ext/opencensus/opencensus_tracing_extension.py
graphene_tornado/ext/opencensus/tests/__init__.py
graphene_tornado/ext/opencensus/tests/test_opencensus_tracing.py
graphene_tornado/tests/__init__.py
graphene_tornado/tests/http_helper.py
graphene_tornado/tests/schema.py
graphene_tornado/tests/test_extensions.py
graphene_tornado/tests/test_graphiql.py
graphene_tornado/tests/test_graphql.py
graphene_tornado-2.6.1.dist-info/LICENSE
graphene_tornado-2.6.1.dist-info/METADATA
graphene_tornado-2.6.1.dist-info/WHEEL
graphene_tornado-2.6.1.dist-info/top_level.txt
graphene_tornado-2.6.1.dist-info/RECORD
