Metadata-Version: 2.1
Name: graphene-tornado
Version: 2.6.1
Summary: Graphene Tornado integration
Home-page: https://github.com/graphql-python/graphene-tornado
Author: Eric Hauser
Author-email: ewhauser@gmail.com
License: MIT
Keywords: api graphql protocol rest relay graphene
Platform: any
Classifier: Development Status :: 3 - Alpha
Classifier: Intended Audience :: Developers
Classifier: Topic :: Software Development :: Libraries
Classifier: Programming Language :: Python :: 2
Classifier: Programming Language :: Python :: 2.7
Classifier: Programming Language :: Python :: 3
Classifier: Programming Language :: Python :: 3.3
Classifier: Programming Language :: Python :: 3.4
Classifier: Programming Language :: Python :: 3.5
Classifier: Programming Language :: Python :: Implementation :: PyPy
Requires-Python: >=3.6
Requires-Dist: six (>=1.10.0)
Requires-Dist: graphene (<3,>=2.1)
Requires-Dist: Jinja2 (>=2.10.1)
Requires-Dist: tornado (>=5.1.0)
Requires-Dist: werkzeug (==0.12.2)
Provides-Extra: apollo-engine-reporting
Requires-Dist: json-stable-stringify-python (==0.2) ; extra == 'apollo-engine-reporting'
Requires-Dist: protobuf (>=3.7.1) ; extra == 'apollo-engine-reporting'
Requires-Dist: tornado-retry-client (==0.6.1) ; extra == 'apollo-engine-reporting'
Provides-Extra: opencensus
Requires-Dist: opencensus (>=0.7.3) ; extra == 'opencensus'
Provides-Extra: test
Requires-Dist: coveralls ; extra == 'test'
Requires-Dist: mock ; extra == 'test'
Requires-Dist: pytest (>=4.4.1) ; extra == 'test'
Requires-Dist: pytest-cov (>=2.6.1) ; extra == 'test'
Requires-Dist: pytest-tornado (>=0.7.0) ; extra == 'test'
Requires-Dist: tox ; extra == 'test'
